sshme/__init__.py
sshme/__main__.py
sshme/menu.py
sshme/ssh.py
sshme/tmux.py
sshme-1.0.0.dist-info/LICENSE
sshme-1.0.0.dist-info/METADATA
sshme-1.0.0.dist-info/WHEEL
sshme-1.0.0.dist-info/entry_points.txt
sshme-1.0.0.dist-info/top_level.txt
sshme-1.0.0.dist-info/RECORD
