Metadata-Version: 2.1
Name: sshme
Version: 1.0.0
Summary: An interactive menu for selecting an SSH profile.
Home-page: https://github.com/kurt-stolle/sshme
Author: Kurt Stolle
Author-email: k.h.w.stolle@gmail.com
License: UNKNOWN
Project-URL: Bug Tracker, https://github.com/kurt-stolle/sshme/issues
Platform: UNKNOWN
Classifier: License :: OSI Approved :: MIT License
Classifier: Operating System :: OS Independent
Classifier: Development Status :: 5 - Production/Stable
Classifier: Environment :: Console
Classifier: Programming Language :: Python :: 3
Classifier: Programming Language :: Python :: Implementation :: CPython
Classifier: Programming Language :: Python :: Implementation :: PyPy
Requires-Python: >=3.6
License-File: LICENSE
Requires-Dist: bullet (==2.2.0)
